[
  {
    "order_id": 6,
    "product_id": 40462,
    "product_name": "Cleanse",
    "status": "delivered",
    "days_since_delivery": 9
  },
  {
    "order_id": 6,
    "product_id": 15873,
    "product_name": "Dryer Sheets Geranium Scent",
    "status": "delivered",
    "days_since_delivery": 7
  },
  {
    "order_id": 6,
    "product_id": 41897,
    "product_name": "Clean Day Lavender Scent Room Freshener Spray",
    "status": "delivered",
    "days_since_delivery": 3
  },
  {
    "order_id": 8,
    "product_id": 23423,
    "product_name": "Original Hawaiian Sweet Rolls",
    "status": "delivered",
    "days_since_delivery": 3
  },
  {
    "order_id": 13,
    "product_id": 17330,
    "product_name": "Light",
    "status": "delivered",
    "days_since_delivery": 8
  },
  {
    "order_id": 13,
    "product_id": 27407,
    "product_name": "Chunky Salsa Medium",
    "status": "delivered",
    "days_since_delivery": 9
  },
  {
    "order_id": 13,
    "product_id": 35419,
    "product_name": "Handmade Vodka From Austin, Texas",
    "status": "refunded",
    "days_since_delivery": 2
  },
  {
    "order_id": 13,
    "product_id": 196,
    "product_name": "Soda",
    "status": "delivered",
    "days_since_delivery": 9
  },
  {
    "order_id": 13,
    "product_id": 44635,
    "product_name": "Salsa Con Queso Medium Dip",
    "status": "refunded",
    "days_since_delivery": 4
  },
  {
    "order_id": 13,
    "product_id": 26878,
    "product_name": "G Series Lime Cucumber Sports Drink",
    "status": "refunded",
    "days_since_delivery": 1
  },
  {
    "order_id": 13,
    "product_id": 25783,
    "product_name": "Lemon Lime Thirst Quencher",
    "status": "refunded",
    "days_since_delivery": 0
  },
  {
    "order_id": 13,
    "product_id": 41290,
    "product_name": "Lemonade",
    "status": "refunded",
    "days_since_delivery": 2
  },
  {
    "order_id": 13,
    "product_id": 33198,
    "product_name": "Sparkling Natural Mineral Water",
    "status": "refunded",
    "days_since_delivery": 6
  },
  {
    "order_id": 13,
    "product_id": 23020,
    "product_name": "Diet Tonic Water",
    "status": "refunded",
    "days_since_delivery": 6
  },
  {
    "order_id": 13,
    "product_id": 36086,
    "product_name": "Philadelphia Original Cream Cheese",
    "status": "refunded",
    "days_since_delivery": 3
  },
  {
    "order_id": 13,
    "product_id": 3800,
    "product_name": "Hampshire 100% Natural Sour Cream",
    "status": "refunded",
    "days_since_delivery": 2
  },
  {
    "order_id": 13,
    "product_id": 25952,
    "product_name": "Original Potato Chips",
    "status": "delivered",
    "days_since_delivery": 9
  },
  {
    "order_id": 14,
    "product_id": 20392,
    "product_name": "Hair Bender Whole Bean Coffee",
    "status": "refunded",
    "days_since_delivery": 6
  },
  {
    "order_id": 14,
    "product_id": 27845,
    "product_name": "Organic Whole Milk",
    "status": "refunded",
    "days_since_delivery": 1
  },
  {
    "order_id": 14,
    "product_id": 162,
    "product_name": "Organic Mini Homestyle Waffles",
    "status": "delivered",
    "days_since_delivery": 8
  },
  {
    "order_id": 14,
    "product_id": 2452,
    "product_name": "Naturals Chicken Nuggets",
    "status": "refunded",
    "days_since_delivery": 2
  },
  {
    "order_id": 14,
    "product_id": 8575,
    "product_name": "Unprocessed American Singles Colby-Style Cheese",
    "status": "delivered",
    "days_since_delivery": 9
  },
  {
    "order_id": 14,
    "product_id": 41890,
    "product_name": "Organic Mesa Sunrise Cereal",
    "status": "refunded",
    "days_since_delivery": 4
  },
  {
    "order_id": 14,
    "product_id": 39475,
    "product_name": "Total Greek Strained Yogurt",
    "status": "refunded",
    "days_since_delivery": 4
  },
  {
    "order_id": 14,
    "product_id": 10096,
    "product_name": "Corn Meal Pizza Crust",
    "status": "refunded",
    "days_since_delivery": 1
  },
  {
    "order_id": 14,
    "product_id": 23032,
    "product_name": "Sriracha Chili Sauce",
    "status": "refunded",
    "days_since_delivery": 0
  },
  {
    "order_id": 14,
    "product_id": 20995,
    "product_name": "Organic Broccoli Florets",
    "status": "delivered",
    "days_since_delivery": 9
  },
  {
    "order_id": 14,
    "product_id": 45066,
    "product_name": "Honeycrisp Apple",
    "status": "delivered",
    "days_since_delivery": 8
  },
  {
    "order_id": 15,
    "product_id": 19660,
    "product_name": "Spring Water",
    "status": "delivered",
    "days_since_delivery": 9
  },
  {
    "order_id": 15,
    "product_id": 21195,
    "product_name": "Organic Extra Virgin Olive Oil",
    "status": "refunded",
    "days_since_delivery": 7
  },
  {
    "order_id": 15,
    "product_id": 7461,
    "product_name": "Pinto Beans No Salt Added",
    "status": "refunded",
    "days_since_delivery": 4
  },
  {
    "order_id": 15,
    "product_id": 2996,
    "product_name": "Honeysuckle Hand Soap",
    "status": "refunded",
    "days_since_delivery": 2
  },
  {
    "order_id": 15,
    "product_id": 32463,
    "product_name": "Olive Oil & Aloe Vera Hand Soap",
    "status": "refunded",
    "days_since_delivery": 6
  },
  {
    "order_id": 19,
    "product_id": 42265,
    "product_name": "Organic Baby Carrots",
    "status": "refunded",
    "days_since_delivery": 5
  },
  {
    "order_id": 19,
    "product_id": 24838,
    "product_name": "Unsweetened Almondmilk",
    "status": "refunded",
    "days_since_delivery": 2
  },
  {
    "order_id": 19,
    "product_id": 41540,
    "product_name": "Organic Whole White Mushrooms",
    "status": "refunded",
    "days_since_delivery": 6
  },
  {
    "order_id": 21,
    "product_id": 5009,
    "product_name": "Yuba Tofu Skin",
    "status": "delivered",
    "days_since_delivery": 8
  },
  {
    "order_id": 21,
    "product_id": 33106,
    "product_name": "Organic Firm Tofu",
    "status": "delivered",
    "days_since_delivery": 5
  },
  {
    "order_id": 21,
    "product_id": 4149,
    "product_name": "Frozen Organic Blueberries",
    "status": "delivered",
    "days_since_delivery": 2
  },
  {
    "order_id": 21,
    "product_id": 31478,
    "product_name": "Dairy-Free Cheddar Style Wedges",
    "status": "delivered",
    "days_since_delivery": 1
  },
  {
    "order_id": 21,
    "product_id": 25718,
    "product_name": "Cold Brew Coffee",
    "status": "delivered",
    "days_since_delivery": 9
  },
  {
    "order_id": 22,
    "product_id": 23909,
    "product_name": "2% Reduced Fat Milk",
    "status": "delivered",
    "days_since_delivery": 8
  },
  {
    "order_id": 22,
    "product_id": 22754,
    "product_name": "Butter Top White Bread",
    "status": "delivered",
    "days_since_delivery": 8
  },
  {
    "order_id": 22,
    "product_id": 24852,
    "product_name": "Banana",
    "status": "delivered",
    "days_since_delivery": 2
  },
  {
    "order_id": 22,
    "product_id": 28993,
    "product_name": "Iceberg Lettuce",
    "status": "delivered",
    "days_since_delivery": 1
  },
  {
    "order_id": 22,
    "product_id": 41273,
    "product_name": "Broccoli Florets",
    "status": "delivered",
    "days_since_delivery": 0
  },
  {
    "order_id": 22,
    "product_id": 23341,
    "product_name": "Large Grade AA Eggs",
    "status": "delivered",
    "days_since_delivery": 3
  },
  {
    "order_id": 22,
    "product_id": 46941,
    "product_name": "Provolone Slices",
    "status": "delivered",
    "days_since_delivery": 2
  },
  {
    "order_id": 22,
    "product_id": 39993,
    "product_name": "Vine Ripe Tomatoes",
    "status": "delivered",
    "days_since_delivery": 2
  },
  {
    "order_id": 22,
    "product_id": 19068,
    "product_name": "Boneless And Skinless Chicken Breast",
    "status": "delivered",
    "days_since_delivery": 0
  },
  {
    "order_id": 22,
    "product_id": 21410,
    "product_name": "Deli Fresh Honey Smoked Turkey Breast, 98% Fat Free, Gluten Free",
    "status": "delivered",
    "days_since_delivery": 8
  },
  {
    "order_id": 22,
    "product_id": 17341,
    "product_name": "Presliced Everything Bagels",
    "status": "delivered",
    "days_since_delivery": 5
  },
  {
    "order_id": 22,
    "product_id": 40593,
    "product_name": "Cream Cheese",
    "status": "delivered",
    "days_since_delivery": 6
  },
  {
    "order_id": 22,
    "product_id": 46979,
    "product_name": "Asparagus",
    "status": "delivered",
    "days_since_delivery": 9
  },
  {
    "order_id": 22,
    "product_id": 31268,
    "product_name": "Sandwich Bags",
    "status": "delivered",
    "days_since_delivery": 3
  },
  {
    "order_id": 23,
    "product_id": 25931,
    "product_name": "Organic Baby Spinach Salad",
    "status": "delivered",
    "days_since_delivery": 6
  },
  {
    "order_id": 23,
    "product_id": 35163,
    "product_name": "Red Leaf Lettuce",
    "status": "delivered",
    "days_since_delivery": 2
  },
  {
    "order_id": 23,
    "product_id": 29662,
    "product_name": "Potato Yukon Gold Organic",
    "status": "delivered",
    "days_since_delivery": 0
  },
  {
    "order_id": 23,
    "product_id": 26283,
    "product_name": "White Corn",
    "status": "delivered",
    "days_since_delivery": 6
  },
  {
    "order_id": 23,
    "product_id": 47766,
    "product_name": "Organic Avocado",
    "status": "delivered",
    "days_since_delivery": 8
  },
  {
    "order_id": 23,
    "product_id": 12036,
    "product_name": "Gluten-Free Supergrain Pasta Organic Corn & Quinoa Blend Penne",
    "status": "delivered",
    "days_since_delivery": 10
  },
  {
    "order_id": 23,
    "product_id": 13497,
    "product_name": "Gluten and Dairy Free Sonoma Veggie Burger",
    "status": "delivered",
    "days_since_delivery": 5
  },
  {
    "order_id": 23,
    "product_id": 44953,
    "product_name": "Organic Three Grain Tempeh",
    "status": "delivered",
    "days_since_delivery": 3
  },
  {
    "order_id": 23,
    "product_id": 7969,
    "product_name": "Lime",
    "status": "delivered",
    "days_since_delivery": 7
  },
  {
    "order_id": 23,
    "product_id": 8518,
    "product_name": "Organic Red Onion",
    "status": "delivered",
    "days_since_delivery": 6
  },
  {
    "order_id": 23,
    "product_id": 18689,
    "product_name": "Dairy-Free Chive Cream Cheese",
    "status": "delivered",
    "days_since_delivery": 8
  },
  {
    "order_id": 23,
    "product_id": 44299,
    "product_name": "Healthy Organic Vinaigrette",
    "status": "delivered",
    "days_since_delivery": 5
  },
  {
    "order_id": 23,
    "product_id": 8381,
    "product_name": "34% Cacao Milk Chocolate Bar",
    "status": "delivered",
    "days_since_delivery": 1
  },
  {
    "order_id": 23,
    "product_id": 32205,
    "product_name": "Fluoride-Free Antiplaque & Whitening Spearmint Toothpaste",
    "status": "delivered",
    "days_since_delivery": 5
  },
  {
    "order_id": 25,
    "product_id": 9755,
    "product_name": "Original Popcorn",
    "status": "delivered",
    "days_since_delivery": 10
  },
  {
    "order_id": 25,
    "product_id": 31487,
    "product_name": "Boomchickapop Sweet & Salty Kettle Corn",
    "status": "delivered",
    "days_since_delivery": 2
  },
  {
    "order_id": 25,
    "product_id": 37510,
    "product_name": "Steamfresh Lightly Sauced Broccoli With Cheese Sauce",
    "status": "delivered",
    "days_since_delivery": 6
  },
  {
    "order_id": 25,
    "product_id": 14576,
    "product_name": "Delights Turkey Sausage Egg Whites & Cheese English Muffin",
    "status": "delivered",
    "days_since_delivery": 6
  },
  {
    "order_id": 25,
    "product_id": 22105,
    "product_name": "Ultra Thin Sliced Provolone Cheese",
    "status": "delivered",
    "days_since_delivery": 9
  },
  {
    "order_id": 25,
    "product_id": 1934,
    "product_name": "Cheese Shredded Mozzarella Reduced Fat 2%",
    "status": "delivered",
    "days_since_delivery": 9
  },
  {
    "order_id": 25,
    "product_id": 6383,
    "product_name": "All Whites 100% Egg Whites",
    "status": "delivered",
    "days_since_delivery": 10
  },
  {
    "order_id": 25,
    "product_id": 39046,
    "product_name": "Smok Cured Turkey Bacon",
    "status": "delivered",
    "days_since_delivery": 1
  },
  {
    "order_id": 25,
    "product_id": 48171,
    "product_name": "Shredded Hash Browns",
    "status": "delivered",
    "days_since_delivery": 9
  },
  {
    "order_id": 25,
    "product_id": 33506,
    "product_name": "Simply 9 White Meat Chicken & Whole Barley Recipe Dog Food",
    "status": "delivered",
    "days_since_delivery": 8
  },
  {
    "order_id": 25,
    "product_id": 30320,
    "product_name": "Craveables Four Cheese Pizza",
    "status": "delivered",
    "days_since_delivery": 4
  },
  {
    "order_id": 25,
    "product_id": 15925,
    "product_name": "Macaroni and Cheese",
    "status": "delivered",
    "days_since_delivery": 2
  },
  {
    "order_id": 25,
    "product_id": 37449,
    "product_name": "Natural Muenster Cheese",
    "status": "delivered",
    "days_since_delivery": 8
  },
  {
    "order_id": 25,
    "product_id": 48299,
    "product_name": "Baby Cut Carrots",
    "status": "delivered",
    "days_since_delivery": 2
  },
  {
    "order_id": 28,
    "product_id": 35108,
    "product_name": "Salted Butter",
    "status": "delivered",
    "days_since_delivery": 9
  },
  {
    "order_id": 28,
    "product_id": 40593,
    "product_name": "Cream Cheese",
    "status": "delivered",
    "days_since_delivery": 1
  },
  {
    "order_id": 28,
    "product_id": 17461,
    "product_name": "Air Chilled Organic Boneless Skinless Chicken Breasts",
    "status": "delivered",
    "days_since_delivery": 5
  },
  {
    "order_id": 28,
    "product_id": 22825,
    "product_name": "Organic D'Anjou Pears",
    "status": "delivered",
    "days_since_delivery": 3
  },
  {
    "order_id": 28,
    "product_id": 25256,
    "product_name": "Cultured Low Fat Buttermilk",
    "status": "delivered",
    "days_since_delivery": 6
  },
  {
    "order_id": 28,
    "product_id": 47626,
    "product_name": "Large Lemon",
    "status": "delivered",
    "days_since_delivery": 4
  },
  {
    "order_id": 28,
    "product_id": 37220,
    "product_name": "Organic Strawberry Fruit Spread",
    "status": "delivered",
    "days_since_delivery": 5
  },
  {
    "order_id": 28,
    "product_id": 12980,
    "product_name": "Large Greenhouse Tomato",
    "status": "delivered",
    "days_since_delivery": 8
  },
  {
    "order_id": 28,
    "product_id": 27548,
    "product_name": "Original Semisoft Cheese",
    "status": "delivered",
    "days_since_delivery": 4
  },
  {
    "order_id": 28,
    "product_id": 45504,
    "product_name": "Whole Organic Omega 3 Milk",
    "status": "delivered",
    "days_since_delivery": 5
  },
  {
    "order_id": 28,
    "product_id": 18531,
    "product_name": "Organic Heavy Whipping Cream",
    "status": "delivered",
    "days_since_delivery": 9
  },
  {
    "order_id": 28,
    "product_id": 47209,
    "product_name": "Organic Hass Avocado",
    "status": "delivered",
    "days_since_delivery": 0
  },
  {
    "order_id": 28,
    "product_id": 24024,
    "product_name": "1% Lowfat Milk",
    "status": "delivered",
    "days_since_delivery": 6
  },
  {
    "order_id": 28,
    "product_id": 38544,
    "product_name": "Organic Whole Milk Strawberry Beet Berry Yogurt Pouch",
    "status": "delivered",
    "days_since_delivery": 4
  },
  {
    "order_id": 28,
    "product_id": 37288,
    "product_name": "Organic Black Plum",
    "status": "delivered",
    "days_since_delivery": 7
  },
  {
    "order_id": 28,
    "product_id": 31915,
    "product_name": "Organic Red Delicious Apple",
    "status": "delivered",
    "days_since_delivery": 9
  },
  {
    "order_id": 29,
    "product_id": 43352,
    "product_name": "Raspberries",
    "status": "delivered",
    "days_since_delivery": 0
  },
  {
    "order_id": 29,
    "product_id": 21386,
    "product_name": "Smartwater",
    "status": "delivered",
    "days_since_delivery": 5
  },
  {
    "order_id": 29,
    "product_id": 13176,
    "product_name": "Bag of Organic Bananas",
    "status": "delivered",
    "days_since_delivery": 6
  },
  {
    "order_id": 29,
    "product_id": 8571,
    "product_name": "Baby Cucumbers",
    "status": "delivered",
    "days_since_delivery": 8
  },
  {
    "order_id": 29,
    "product_id": 33768,
    "product_name": "Sinfully Sweet Campari Tomatoes",
    "status": "delivered",
    "days_since_delivery": 7
  },
  {
    "order_id": 37,
    "product_id": 35561,
    "product_name": "Organic Tortilla Chips",
    "status": "delivered",
    "days_since_delivery": 9
  },
  {
    "order_id": 37,
    "product_id": 33059,
    "product_name": "Ice Peppermint Gum",
    "status": "delivered",
    "days_since_delivery": 8
  },
  {
    "order_id": 37,
    "product_id": 43721,
    "product_name": "Wint-O-Green",
    "status": "delivered",
    "days_since_delivery": 4
  },
  {
    "order_id": 40,
    "product_id": 10070,
    "product_name": "Organic 1% Low Fat Milk",
    "status": "delivered",
    "days_since_delivery": 0
  },
  {
    "order_id": 40,
    "product_id": 42450,
    "product_name": "Macaroni & Cheese",
    "status": "delivered",
    "days_since_delivery": 3
  },
  {
    "order_id": 40,
    "product_id": 33198,
    "product_name": "Sparkling Natural Mineral Water",
    "status": "delivered",
    "days_since_delivery": 6
  },
  {
    "order_id": 40,
    "product_id": 34866,
    "product_name": "Chocolate Milk 1% Milkfat",
    "status": "delivered",
    "days_since_delivery": 6
  },
  {
    "order_id": 41,
    "product_id": 27344,
    "product_name": "Uncured Genoa Salami",
    "status": "delivered",
    "days_since_delivery": 8
  },
  {
    "order_id": 41,
    "product_id": 27355,
    "product_name": "All Natural Seasoned Waffle Cut Fries",
    "status": "delivered",
    "days_since_delivery": 9
  },
  {
    "order_id": 42,
    "product_id": 19887,
    "product_name": "Unsweetened Vanilla Almond Breeze",
    "status": "delivered",
    "days_since_delivery": 0
  },
  {
    "order_id": 42,
    "product_id": 33000,
    "product_name": "Pure Irish Butter",
    "status": "delivered",
    "days_since_delivery": 1
  },
  {
    "order_id": 42,
    "product_id": 13176,
    "product_name": "Bag of Organic Bananas",
    "status": "delivered",
    "days_since_delivery": 9
  },
  {
    "order_id": 43,
    "product_id": 20915,
    "product_name": "Mozzarella Light Low Moisture Part Skim String Cheese",
    "status": "delivered",
    "days_since_delivery": 5
  },
  {
    "order_id": 43,
    "product_id": 21949,
    "product_name": "White Cheddar Semisoft Cheese",
    "status": "delivered",
    "days_since_delivery": 9
  },
  {
    "order_id": 43,
    "product_id": 8817,
    "product_name": "13 Gallon Kitchen Drawstring Trash Bags",
    "status": "delivered",
    "days_since_delivery": 10
  },
  {
    "order_id": 43,
    "product_id": 37867,
    "product_name": "Classic Variety Pack Donuts",
    "status": "delivered",
    "days_since_delivery": 1
  },
  {
    "order_id": 43,
    "product_id": 12850,
    "product_name": "Original Denture Adhesive Cream",
    "status": "delivered",
    "days_since_delivery": 8
  },
  {
    "order_id": 43,
    "product_id": 21553,
    "product_name": "Lowfat 2% Milkfat Cottage Cheese",
    "status": "delivered",
    "days_since_delivery": 5
  },
  {
    "order_id": 43,
    "product_id": 34005,
    "product_name": "Black Seedless Grapes",
    "status": "delivered",
    "days_since_delivery": 9
  },
  {
    "order_id": 45,
    "product_id": 16349,
    "product_name": "Organic Yams",
    "status": "delivered",
    "days_since_delivery": 6
  },
  {
    "order_id": 46,
    "product_id": 36884,
    "product_name": "Pain Reliever/Fever Reducer (NSAID), Ibuprofen 200mg",
    "status": "refunded",
    "days_since_delivery": 6
  },
  {
    "order_id": 46,
    "product_id": 48183,
    "product_name": "Flour Tortillas",
    "status": "delivered",
    "days_since_delivery": 8
  },
  {
    "order_id": 46,
    "product_id": 26172,
    "product_name": "Light Sour Cream",
    "status": "delivered",
    "days_since_delivery": 9
  },
  {
    "order_id": 46,
    "product_id": 4778,
    "product_name": "Wheat Thins Reduced Fat Crackers",
    "status": "delivered",
    "days_since_delivery": 9
  },
  {
    "order_id": 46,
    "product_id": 34519,
    "product_name": "Simply 100\u00ae Blueberry Blended Non-Fat Greek Yogurt",
    "status": "refunded",
    "days_since_delivery": 2
  },
  {
    "order_id": 46,
    "product_id": 11983,
    "product_name": "Simply 100 Strawberry Blended Non-Fat Greek Yogurt",
    "status": "delivered",
    "days_since_delivery": 8
  },
  {
    "order_id": 46,
    "product_id": 18346,
    "product_name": "90 Calories Low Fat Chocolate Chunk Granola Bars",
    "status": "delivered",
    "days_since_delivery": 8
  },
  {
    "order_id": 46,
    "product_id": 21067,
    "product_name": "Reduced Fat Sliced Provolone Cheese",
    "status": "refunded",
    "days_since_delivery": 6
  },
  {
    "order_id": 46,
    "product_id": 41602,
    "product_name": "Deli Select Ultra Thin Honey Ham",
    "status": "refunded",
    "days_since_delivery": 6
  },
  {
    "order_id": 46,
    "product_id": 27656,
    "product_name": "Reduced Sugar Mixed Fruit Fruit Snacks",
    "status": "refunded",
    "days_since_delivery": 7
  },
  {
    "order_id": 46,
    "product_id": 17417,
    "product_name": "Reduced Fat Original Potato Crisps",
    "status": "refunded",
    "days_since_delivery": 7
  },
  {
    "order_id": 46,
    "product_id": 22282,
    "product_name": "Ultra Soft Bathroom Tissue, Double Rolls",
    "status": "refunded",
    "days_since_delivery": 3
  },
  {
    "order_id": 46,
    "product_id": 47827,
    "product_name": "Cafe Steamers General Tso's Spicy Chicken",
    "status": "refunded",
    "days_since_delivery": 4
  },
  {
    "order_id": 46,
    "product_id": 32917,
    "product_name": "Chicken Marsala",
    "status": "refunded",
    "days_since_delivery": 1
  },
  {
    "order_id": 46,
    "product_id": 5077,
    "product_name": "100% Whole Wheat Bread",
    "status": "refunded",
    "days_since_delivery": 3
  },
  {
    "order_id": 46,
    "product_id": 4447,
    "product_name": "Berries 'n Cherries Fruit Snacks",
    "status": "refunded",
    "days_since_delivery": 1
  },
  {
    "order_id": 46,
    "product_id": 3703,
    "product_name": "Plates, 10-1/16 Inch",
    "status": "refunded",
    "days_since_delivery": 6
  },
  {
    "order_id": 46,
    "product_id": 34233,
    "product_name": "Casual Napkins",
    "status": "refunded",
    "days_since_delivery": 7
  },
  {
    "order_id": 46,
    "product_id": 28921,
    "product_name": "Original",
    "status": "delivered",
    "days_since_delivery": 9
  },
  {
    "order_id": 46,
    "product_id": 15364,
    "product_name": "Thick 'N Creamy Macaroni & Cheese",
    "status": "refunded",
    "days_since_delivery": 0
  },
  {
    "order_id": 49,
    "product_id": 3513,
    "product_name": "Organic Blueberry",
    "status": "delivered",
    "days_since_delivery": 0
  },
  {
    "order_id": 49,
    "product_id": 39276,
    "product_name": "Bananas",
    "status": "delivered",
    "days_since_delivery": 8
  },
  {
    "order_id": 49,
    "product_id": 20307,
    "product_name": "Single Origin 3",
    "status": "delivered",
    "days_since_delivery": 1
  },
  {
    "order_id": 49,
    "product_id": 19677,
    "product_name": "Original Pure Creamy Almond Milk",
    "status": "delivered",
    "days_since_delivery": 5
  },
  {
    "order_id": 50,
    "product_id": 397,
    "product_name": "Pure Granulated Cane Sugar",
    "status": "delivered",
    "days_since_delivery": 0
  },
  {
    "order_id": 50,
    "product_id": 34993,
    "product_name": "Mango Yoghurt",
    "status": "delivered",
    "days_since_delivery": 3
  },
  {
    "order_id": 50,
    "product_id": 17183,
    "product_name": "Peach Yoghurt",
    "status": "delivered",
    "days_since_delivery": 6
  },
  {
    "order_id": 50,
    "product_id": 37788,
    "product_name": "All Natural Gluten Free Probiotic Pineapple Yoghurt",
    "status": "delivered",
    "days_since_delivery": 3
  },
  {
    "order_id": 50,
    "product_id": 1025,
    "product_name": "Organic Fresh Basil",
    "status": "delivered",
    "days_since_delivery": 3
  },
  {
    "order_id": 50,
    "product_id": 4799,
    "product_name": "Shredded Parmesan",
    "status": "delivered",
    "days_since_delivery": 0
  },
  {
    "order_id": 50,
    "product_id": 276,
    "product_name": "French Vanilla Ice Cream",
    "status": "delivered",
    "days_since_delivery": 3
  },
  {
    "order_id": 52,
    "product_id": 18963,
    "product_name": "Apple Cider Vinegar",
    "status": "delivered",
    "days_since_delivery": 8
  },
  {
    "order_id": 52,
    "product_id": 24852,
    "product_name": "Banana",
    "status": "delivered",
    "days_since_delivery": 6
  },
  {
    "order_id": 52,
    "product_id": 39408,
    "product_name": "Gala Apples",
    "status": "delivered",
    "days_since_delivery": 7
  },
  {
    "order_id": 52,
    "product_id": 49683,
    "product_name": "Cucumber Kirby",
    "status": "delivered",
    "days_since_delivery": 1
  },
  {
    "order_id": 52,
    "product_id": 4485,
    "product_name": "Cinnamon Raisin Granola",
    "status": "delivered",
    "days_since_delivery": 1
  },
  {
    "order_id": 53,
    "product_id": 24852,
    "product_name": "Banana",
    "status": "delivered",
    "days_since_delivery": 9
  },
  {
    "order_id": 53,
    "product_id": 37646,
    "product_name": "Organic Gala Apples",
    "status": "delivered",
    "days_since_delivery": 9
  },
  {
    "order_id": 53,
    "product_id": 47209,
    "product_name": "Organic Hass Avocado",
    "status": "delivered",
    "days_since_delivery": 10
  },
  {
    "order_id": 53,
    "product_id": 36606,
    "product_name": "Sprouted Multi-Grain Bread",
    "status": "refunded",
    "days_since_delivery": 4
  },
  {
    "order_id": 53,
    "product_id": 32442,
    "product_name": "Organic Original Tofu Veggie Burger",
    "status": "refunded",
    "days_since_delivery": 2
  },
  {
    "order_id": 53,
    "product_id": 14467,
    "product_name": "Sweet Baguette",
    "status": "refunded",
    "days_since_delivery": 5
  },
  {
    "order_id": 53,
    "product_id": 40706,
    "product_name": "Organic Grape Tomatoes",
    "status": "delivered",
    "days_since_delivery": 9
  },
  {
    "order_id": 53,
    "product_id": 5876,
    "product_name": "Organic Lemon",
    "status": "refunded",
    "days_since_delivery": 6
  },
  {
    "order_id": 53,
    "product_id": 22298,
    "product_name": "Yo Baby Organic Whole Milk Banana Mango Yogurt",
    "status": "refunded",
    "days_since_delivery": 2
  },
  {
    "order_id": 53,
    "product_id": 38827,
    "product_name": "Organic Traditional Flour Tortillas",
    "status": "refunded",
    "days_since_delivery": 3
  },
  {
    "order_id": 53,
    "product_id": 39275,
    "product_name": "Organic Blueberries",
    "status": "refunded",
    "days_since_delivery": 6
  },
  {
    "order_id": 53,
    "product_id": 38647,
    "product_name": "Organic Raw Sharp Cheddar Cheese",
    "status": "delivered",
    "days_since_delivery": 8
  },
  {
    "order_id": 53,
    "product_id": 47626,
    "product_name": "Large Lemon",
    "status": "refunded",
    "days_since_delivery": 5
  },
  {
    "order_id": 53,
    "product_id": 34448,
    "product_name": "Original Veggie Straws",
    "status": "refunded",
    "days_since_delivery": 1
  },
  {
    "order_id": 53,
    "product_id": 46194,
    "product_name": "Burrata",
    "status": "refunded",
    "days_since_delivery": 5
  },
  {
    "order_id": 54,
    "product_id": 10833,
    "product_name": "Instant French Vanilla Pudding & Pie Filling",
    "status": "refunded",
    "days_since_delivery": 4
  },
  {
    "order_id": 54,
    "product_id": 24852,
    "product_name": "Banana",
    "status": "refunded",
    "days_since_delivery": 1
  },
  {
    "order_id": 54,
    "product_id": 34004,
    "product_name": "Mixed Berries Wildly Nutritious Signature Blends",
    "status": "refunded",
    "days_since_delivery": 5
  },
  {
    "order_id": 54,
    "product_id": 35430,
    "product_name": "Nilla Wafers",
    "status": "delivered",
    "days_since_delivery": 8
  },
  {
    "order_id": 54,
    "product_id": 11121,
    "product_name": "Original Whipped Topping",
    "status": "refunded",
    "days_since_delivery": 6
  },
  {
    "order_id": 54,
    "product_id": 36086,
    "product_name": "Philadelphia Original Cream Cheese",
    "status": "delivered",
    "days_since_delivery": 10
  },
  {
    "order_id": 54,
    "product_id": 32971,
    "product_name": "Sliced Peaches",
    "status": "refunded",
    "days_since_delivery": 6
  },
  {
    "order_id": 56,
    "product_id": 7021,
    "product_name": "Organic Tomato Paste",
    "status": "delivered",
    "days_since_delivery": 1
  },
  {
    "order_id": 56,
    "product_id": 4799,
    "product_name": "Shredded Parmesan",
    "status": "delivered",
    "days_since_delivery": 8
  },
  {
    "order_id": 56,
    "product_id": 24964,
    "product_name": "Organic Garlic",
    "status": "delivered",
    "days_since_delivery": 10
  },
  {
    "order_id": 56,
    "product_id": 11520,
    "product_name": "Large Alfresco Eggs",
    "status": "delivered",
    "days_since_delivery": 10
  },
  {
    "order_id": 56,
    "product_id": 9076,
    "product_name": "Blueberries",
    "status": "delivered",
    "days_since_delivery": 0
  },
  {
    "order_id": 56,
    "product_id": 1376,
    "product_name": "Buttermilk Biscuits",
    "status": "delivered",
    "days_since_delivery": 0
  },
  {
    "order_id": 56,
    "product_id": 47209,
    "product_name": "Organic Hass Avocado",
    "status": "delivered",
    "days_since_delivery": 6
  },
  {
    "order_id": 56,
    "product_id": 21903,
    "product_name": "Organic Baby Spinach",
    "status": "delivered",
    "days_since_delivery": 3
  },
  {
    "order_id": 56,
    "product_id": 21910,
    "product_name": "Coconut Almond Creamer Blend",
    "status": "delivered",
    "days_since_delivery": 0
  },
  {
    "order_id": 56,
    "product_id": 34050,
    "product_name": "Orange Juice",
    "status": "delivered",
    "days_since_delivery": 0
  },
  {
    "order_id": 57,
    "product_id": 21903,
    "product_name": "Organic Baby Spinach",
    "status": "refunded",
    "days_since_delivery": 2
  },
  {
    "order_id": 57,
    "product_id": 47231,
    "product_name": "Ultra-Purified Water",
    "status": "refunded",
    "days_since_delivery": 3
  },
  {
    "order_id": 57,
    "product_id": 21137,
    "product_name": "Organic Strawberries",
    "status": "delivered",
    "days_since_delivery": 9
  },
  {
    "order_id": 57,
    "product_id": 43122,
    "product_name": "Organic Bartlett Pear",
    "status": "delivered",
    "days_since_delivery": 8
  },
  {
    "order_id": 57,
    "product_id": 19057,
    "product_name": "Organic Large Extra Fancy Fuji Apple",
    "status": "refunded",
    "days_since_delivery": 4
  },
  {
    "order_id": 57,
    "product_id": 47209,
    "product_name": "Organic Hass Avocado",
    "status": "refunded",
    "days_since_delivery": 6
  },
  {
    "order_id": 57,
    "product_id": 48857,
    "product_name": "Authentic French Brioche",
    "status": "refunded",
    "days_since_delivery": 3
  },
  {
    "order_id": 60,
    "product_id": 9934,
    "product_name": "Organic Australian Style Vanilla Lowfat Yogurt",
    "status": "delivered",
    "days_since_delivery": 3
  }
]